edmlib/__init__.py
edmlib/edm/__init__.py
edmlib/edm/base.py
edmlib/edm/classes/__init__.py
edmlib/edm/classes/context.py
edmlib/edm/classes/core.py
edmlib/edm/classes/service.py
edmlib/edm/edm_jsonld_frame.jsonld
edmlib/edm/enums.py
edmlib/edm/exceptions.py
edmlib/edm/jsonld_cached_documentloader.py
edmlib/edm/record.py
edmlib/edm/validation/__init__.py
edmlib/edm/validation/edm_rights.py
edmlib/edm/validation/uri.py
edmlib/edm/value_types.py
edmlib/parser.py
edmlib/shared_types.py
edmlib-2.5.3.dist-info/METADATA
edmlib-2.5.3.dist-info/WHEEL
edmlib-2.5.3.dist-info/entry_points.txt
edmlib-2.5.3.dist-info/RECORD
