Metadata-Version: 2.1
Name: edmlib
Version: 2.5.3
Summary: Provides comprehensive mapping of all EDM classes and properties to Pydantic models and attributes, enabling robust data validation and serialization. Includes parsing capabilities for XML EDM files, allowing seamless conversion of XML data into Python objects for further processing and analysis. 
License: MIT
Author: Kulturpool
Author-email: info@kulturpool.at
Requires-Python: >=3.10,<4.0.0
Classifier: License :: OSI Approved :: MIT License
Classifier: Programming Language :: Python :: 3
Classifier: Programming Language :: Python :: 3.10
Classifier: Programming Language :: Python :: 3.11
Classifier: Programming Language :: Python :: 3.12
Classifier: Programming Language :: Python :: 3.13
Requires-Dist: lxml (>=5.1.0,<6.0.0)
Requires-Dist: pdoc (>=15.0.4,<16.0.0)
Requires-Dist: pydantic (>=2.10.3,<3.0.0)
Requires-Dist: pyld (>=2.0.3,<3.0.0)
Requires-Dist: rdflib (>=7.0.0,<8.0.0)
Requires-Dist: requests (>=2.32.3,<3.0.0)
